bronchipy/__init__.py
bronchipy/airwaytree.py
bronchipy/calc/__init__.py
bronchipy/calc/measure_airways.py
bronchipy/calc/summary_stats.py
bronchipy/calc/visualise.py
bronchipy/io/__init__.py
bronchipy/io/branchio.py
bronchipy/io/config.py
bronchipy/util/__init__.py
bronchipy/util/filereaders.py
bronchipy/util/functionsutil.py
bronchipy/util/imagefilereaders.py
bronchipy/util/imageoperations.py
bronchipy-0.0.9.dist-info/LICENCE
bronchipy-0.0.9.dist-info/METADATA
bronchipy-0.0.9.dist-info/WHEEL
bronchipy-0.0.9.dist-info/top_level.txt
bronchipy-0.0.9.dist-info/RECORD
