Metadata-Version: 2.1
Name: bronchipy
Version: 0.0.9
Summary: Supporting tools for processing the output of the AirFlow pipeline.
Author: ImaLife
Author-email: <i.dudurych@umcg.nl>
License: UNKNOWN
Keywords: python,analysis,medical,imaging,research
Platform: UNKNOWN
Classifier: Development Status :: 3 - Alpha
Classifier: Intended Audience :: Science/Research
Classifier: Programming Language :: Python :: 3
Classifier: Operating System :: Unix
Classifier: Operating System :: MacOS :: MacOS X
Classifier: Operating System :: Microsoft :: Windows
License-File: LICENCE
Requires-Dist: nibabel (==4.0.1)
Requires-Dist: pydicom (==2.3.0)
Requires-Dist: numpy (==1.19.2)
Requires-Dist: pandas (==1.4.3)
Requires-Dist: scipy (==1.5.3)
Requires-Dist: scikit-learn (==1.1.2)
Requires-Dist: matplotlib (==3.3.4)
Requires-Dist: SimpleITK (==1.2.4)
Requires-Dist: scikit-image (==0.19.3)
